[
  {
    "name": "Engine",
    "description": "High quality services of construction industries",
    "quantity": "1",
    "price": "$100",
    "image": "https://i.ibb.co/D5D5YNc/gcb8.jpg",
    "available": "100"
  },
  {
    "name": "Engine",
    "description": "High quality services of construction industries",
    "quantity": "1",
    "price": "$100",
    "image": "https://i.ibb.co/D5D5YNc/gcb8.jpg",
    "available": "100"
  },
  {
    "name": "Engine",
    "description": "High quality services of construction industries",
    "quantity": "1",
    "price": "$100",
    "image": "https://i.ibb.co/D5D5YNc/gcb8.jpg",
    "available": "100"
  }
]
